campo_estatico_mdf/__init__.py
campo_estatico_mdf/solver.py
campo_estatico_mdf_ds-0.1.0.dist-info/licenses/LICENSE
campo_estatico_mdf_ds-0.1.0.dist-info/METADATA
campo_estatico_mdf_ds-0.1.0.dist-info/WHEEL
campo_estatico_mdf_ds-0.1.0.dist-info/top_level.txt
campo_estatico_mdf_ds-0.1.0.dist-info/RECORD
