Metadata-Version: 2.4
Name: campo_estatico_mdf-DS
Version: 0.1.0
Summary: Un paquete para resolver el campo electrostático 2D con el Método de Diferencias Finitas.
Author-email: Camilo Huertas <cahuertasa@udistrital.edu.co>, Sebastian Rodriguez <sebrodriguezg@udistrital.edu.co>, Julian Avila <jlavilam@udistrital.edu.co>
Classifier: Programming Language :: Python :: 3
Classifier: License :: OSI Approved :: MIT License
Classifier: Operating System :: OS Independent
Requires-Python: >=3.8
License-File: LICENSE
Requires-Dist: numpy
Requires-Dist: scipy
Requires-Dist: matplotlib
Requires-Dist: pytest
Dynamic: license-file
